avwx/__init__.py
avwx/models.py
avwx-1.0.0.dist-info/METADATA
avwx-1.0.0.dist-info/RECORD
avwx-1.0.0.dist-info/WHEEL
avwx-1.0.0.dist-info/top_level.txt
