Metadata-Version: 2.1
Name: avwx
Version: 1.0.0
Summary: A tool to grab aviation-related weather
Home-page: https://github.com/cloudrave/avwx
Author: Nick Merrill
Author-email: public@nickmerrill.co
License: MIT
Keywords: aviation-weather
Platform: UNKNOWN
Classifier: Development Status :: 3 - Alpha
Classifier: Intended Audience :: Developers
Classifier: License :: OSI Approved :: MIT License
Classifier: Programming Language :: Python :: 3
Requires-Dist: python-dateutil
